LICENSE.txt
MANIFEST.in
README.rst
setup.cfg
setup.py
pyarubaoss/__init__.py
pyarubaoss/auth.py
pyarubaoss/ip.py
pyarubaoss/mactable.py
pyarubaoss/mstp.py
pyarubaoss/poe.py
pyarubaoss/ports.py
pyarubaoss/system.py
pyarubaoss/vlans.py
pyarubaoss.egg-info/PKG-INFO
pyarubaoss.egg-info/SOURCES.txt
pyarubaoss.egg-info/dependency_links.txt
pyarubaoss.egg-info/entry_points.txt
pyarubaoss.egg-info/requires.txt
pyarubaoss.egg-info/top_level.txt