Metadata-Version: 1.1
Name: pyarubaoss
Version: 1.0.3
Summary: Python binding for HPE Aruba OS Switch REST API Interface
Home-page: https://github.com/HPENetworking/pyarubaaoss
Author: netmanchris
Author-email: chris_young@me.com
License: Apache2
Keywords: HPE ArubaOS Switch RESTFUL API
Platform: UNKNOWN
Classifier: Development Status :: 4 - Beta
Classifier: Intended Audience :: Developers
Classifier: Intended Audience :: System Administrators
Classifier: License :: OSI Approved :: Apache Software License
Classifier: Programming Language :: Python
Classifier: Natural Language :: English
Classifier: Operating System :: OS Independent
Classifier: Topic :: Software Development :: Libraries :: Python Modules
